illico/__init__.py
illico/asymptotic_wilcoxon.py
illico/ovo/__init__.py
illico/ovo/dense_ovo.py
illico/ovo/sparse_ovo.py
illico/ovr/__init__.py
illico/ovr/dense_ovr.py
illico/ovr/sparse_ovr.py
illico/utils/__init__.py
illico/utils/compile.py
illico/utils/groups.py
illico/utils/math.py
illico/utils/memory.py
illico/utils/ranking.py
illico/utils/registry.py
illico/utils/sparse/__init__.py
illico/utils/sparse/csc.py
illico/utils/sparse/csr.py
illico/utils/type.py
illico-0.2.0.dist-info/METADATA
illico-0.2.0.dist-info/WHEEL
illico-0.2.0.dist-info/licenses/LICENSE
illico-0.2.0.dist-info/RECORD
