Metadata-Version: 2.4
Name: illico
Version: 0.2.0
Summary: Fast asymptotic mannwhitney-u test
License-File: LICENSE
Author: remydubois
Author-email: remydubois14@gmail.com
Requires-Python: >=3.11,<4.0
Classifier: Programming Language :: Python :: 3
Classifier: Programming Language :: Python :: 3.11
Classifier: Programming Language :: Python :: 3.12
Classifier: Programming Language :: Python :: 3.13
Classifier: Programming Language :: Python :: 3.14
Requires-Dist: anndata (>=0.11)
Requires-Dist: joblib (>=1.5.3,<2.0.0)
Requires-Dist: loguru (>=0.7.3,<0.8.0)
Requires-Dist: numba (>=0.63.1,<0.64.0)
Requires-Dist: pandas (>=2.3.3,<3.0.0)
Requires-Dist: scipy (>=1.16.3,<2.0.0)
Requires-Dist: tqdm (>=4.67.1,<5.0.0)
